flights_time_series_dataset/__init__.py
flights_time_series_dataset/convert_year_month_array_to_datetime.py
flights_time_series_dataset/flight_series_dataset.py
flights_time_series_dataset/flights_dataset.py
tests/fixtures/__init__.py
tests/fixtures/expected_results.py
flights_time_series_dataset-1.1.10.dist-info/LICENSE
flights_time_series_dataset-1.1.10.dist-info/METADATA
flights_time_series_dataset-1.1.10.dist-info/WHEEL
flights_time_series_dataset-1.1.10.dist-info/top_level.txt
flights_time_series_dataset-1.1.10.dist-info/RECORD
