Metadata-Version: 2.1
Name: flights-time-series-dataset
Version: 1.1.10
Summary: Flights time series dataset for time-series-predictor.
Home-page: https://github.com/krypton-unite/flights_time_series_dataset.git
Author: Daniel Kaminski de Souza
Author-email: daniel@kryptonunite.com
License: The Unlicense
Download-URL: https://pypi.org/project/flights-time-series-dataset/
Keywords: Time series dataset
Platform: UNKNOWN
Requires-Python: >=3.7
Requires-Dist: time-series-dataset-generator
Requires-Dist: seaborn
Provides-Extra: dev
Requires-Dist: bumpversion ; extra == 'dev'
Requires-Dist: twine ; extra == 'dev'
Requires-Dist: wheel ; extra == 'dev'
Requires-Dist: pylint ; extra == 'dev'
Requires-Dist: autopep8 ; extra == 'dev'
Provides-Extra: test
Requires-Dist: pytest ; extra == 'test'
Requires-Dist: pytest-cov ; extra == 'test'
